app/__init__.py
app/db.py
app/favicon.ico
app/flask_app.py
app/generate_thumbnails.py
app/launcher_backend_userList.py
app/main.py
app/metadidomi_cloud_storage.py
app/models.py
app/routes.py
app/schemas.py
app/test_auth_cloud_database.py
app/version.txt
app/routers/admin.py
app/routers/users.py
app/services/__init__.py
app/services/dynamic_routes.py
app/static/admin.js
app/static/alert-popup.css
app/static/alert.css
app/static/cloud_database.js
app/static/cloud_database_style.css
app/static/cloud_drive.css
app/static/cloud_drive.js
app/static/cloud_files.css
app/static/cloud_files.js
app/static/favicon.ico
app/static/style.css
app/static/icons/.keep
app/templates/admin.html
app/templates/api_stats.html
app/templates/cloud_database.html
app/templates/cloud_drive.html
app/templates/cloud_files.html
app/templates/login.html
app/templates/main_ui.html
app/templates/search_template.html
app/templates/usersList.html
metadidomi_server_plus-1.0.1.dist-info/licenses/license.txt
metadidomi_server_plus-1.0.1.dist-info/METADATA
metadidomi_server_plus-1.0.1.dist-info/WHEEL
metadidomi_server_plus-1.0.1.dist-info/entry_points.txt
metadidomi_server_plus-1.0.1.dist-info/top_level.txt
metadidomi_server_plus-1.0.1.dist-info/RECORD
